Workbook

Sheet Dashboard
A1: AURA ANDERMATT — DASHBOARD
A3: KEY METRICS | B3: Downside | C3: Base | D3: Upside
A4: 10-Year Cumulative Cash (CHF) | B4: =K32 | C4: =K20 | D4: =K44
A5: 2027 Profit After Tax (CHF) | B5: =B31 | C5: =B19 | D5: =B43
A9: SCENARIO COMPARISON (10-YEAR P&L)
A10: BASE SCENARIO
B11: 2027 | C11: 2028 | D11: 2029 | E11: 2030 | F11: 2031 | G11: 2032 | H11: 2033 | I11: 2034 | J11: 2035 | K11: 2036
A12: Net Ticket Revenue | B12: ='P&L'!B10*$C$60*$C$61 | C12: ='P&L'!C10*$C$60*$C$61 | D12: ='P&L'!D10*$C$60*$C$61 | E12: ='P&L'!E10*$C$60*$C$61 | F12: ='P&L'!F10*$C$60*$C$61 | G12: ='P&L'!G10*$C$60*$C$61 | H12: ='P&L'!H10*$C$60*$C$61 | I12: ='P&L'!I10*$C$60*$C$61 | ... K12: ='P&L'!K10*$C$60*$C$61
A13: Partnership Revenue | B13: ='P&L'!B11*$C$62 | C13: ='P&L'!C11*$C$62 | D13: ='P&L'!D11*$C$62 | E13: ='P&L'!E11*$C$62 | F13: ='P&L'!F11*$C$62 | G13: ='P&L'!G11*$C$62 | H13: ='P&L'!H11*$C$62 | I13: ='P&L'!I11*$C$62 | ... K13: ='P&L'!K11*$C$62
A14: Other Revenue (ASA+F&B+Dinner+Other) | B14: ='P&L'!B12*$C$63+'P&L'!B13+'P&L'!B14+'P&L'!B15 | C14: ='P&L'!C12*$C$63+'P&L'!C13+'P&L'!C14+'P&L'!C15 | D14: ='P&L'!D12*$C$63+'P&L'!D13+'P&L'!D14+'P&L'!D15 | E14: ='P&L'!E12*$C$63+'P&L'!E13+'P&L'!E14+'P&L'!E15 | F14: ='P&L'!F12*$C$63+'P&L'!F13+'P&L'!F14+'P&L'!F15 | G14: ='P&L'!G12*$C$63+'P&L'!G13+'P&L'!G14+'P&L'!G15 | H14: ='P&L'!H12*$C$63+'P&L'!H13+'P&L'!H14+'P&L'!H15 | I14: ='P&L'!I12*$C$63+'P&L'!I13+'P&L'!I14+'P&L'!I15 | ... K14: ='P&L'!K12*$C$63+'P&L'!K13+'P&L'!K14+'P&L'!K15
A15: Total Revenue | B15: =(B12+B13+B14)*(1+IF(2027>=$C$71,Revenue!$B$11,0)) | C15: =(C12+C13+C14)*(1+IF(2028>=$C$71,Revenue!$B$11,0)) | D15: =(D12+D13+D14)*(1+IF(2029>=$C$71,Revenue!$B$11,0)) | E15: =(E12+E13+E14)*(1+IF(2030>=$C$71,Revenue!$B$11,0)) | F15: =(F12+F13+F14)*(1+IF(2031>=$C$71,Revenue!$B$11,0)) | G15: =(G12+G13+G14)*(1+IF(2032>=$C$71,Revenue!$B$11,0)) | H15: =(H12+H13+H14)*(1+IF(2033>=$C$71,Revenue!$B$11,0)) | I15: =(I12+I13+I14)*(1+IF(2034>=$C$71,Revenue!$B$11,0)) | J15: =(J12+J13+J14)*(1+IF(2035>=$C$71,Revenue!$B$11,0)) | K15: =(K12+K13+K14)*(1+IF(2036>=$C$71,Revenue!$B$11,0))
A16: Total Costs | B16: ='P&L'!B20*$C$66+'P&L'!B21+'P&L'!B22*$C$67 | C16: ='P&L'!C20*$C$66+'P&L'!C21+'P&L'!C22*$C$67 | D16: ='P&L'!D20*$C$66+'P&L'!D21+'P&L'!D22*$C$67 | E16: ='P&L'!E20*$C$66+'P&L'!E21+'P&L'!E22*$C$67 | F16: ='P&L'!F20*$C$66+'P&L'!F21+'P&L'!F22*$C$67 | G16: ='P&L'!G20*$C$66+'P&L'!G21+'P&L'!G22*$C$67 | H16: ='P&L'!H20*$C$66+'P&L'!H21+'P&L'!H22*$C$67 | I16: ='P&L'!I20*$C$66+'P&L'!I21+'P&L'!I22*$C$67 | ... K16: ='P&L'!K20*$C$66+'P&L'!K21+'P&L'!K22*$C$67
A17: EBIT | B17: =B15+B16 | C17: =C15+C16 | D17: =D15+D16 | E17: =E15+E16 | F17: =F15+F16 | G17: =G15+G16 | H17: =H15+H16 | I17: =I15+I16 | ... K17: =K15+K16
A18: Tax | B18: =IF(B17>0,-B17*'P&L'!$B$5,0) | C18: =IF(C17>0,-C17*'P&L'!$B$5,0) | D18: =IF(D17>0,-D17*'P&L'!$B$5,0) | E18: =IF(E17>0,-E17*'P&L'!$B$5,0) | F18: =IF(F17>0,-F17*'P&L'!$B$5,0) | G18: =IF(G17>0,-G17*'P&L'!$B$5,0) | H18: =IF(H17>0,-H17*'P&L'!$B$5,0) | I18: =IF(I17>0,-I17*'P&L'!$B$5,0) | ... K18: =IF(K17>0,-K17*'P&L'!$B$5,0)
A19: Profit After Tax | B19: =B17+B18 | C19: =C17+C18 | D19: =D17+D18 | E19: =E17+E18 | F19: =F17+F18 | G19: =G17+G18 | H19: =H17+H18 | I19: =I17+I18 | ... K19: =K17+K18
A20: Cumulative Cash | B20: ='P&L'!$B$6+B19 | C20: =B20+C19 | D20: =C20+D19 | E20: =D20+E19 | F20: =E20+F19 | G20: =F20+G19 | H20: =G20+H19 | I20: =H20+I19 | J20: =I20+J19 | K20: =J20+K19
A22: DOWNSIDE SCENARIO
B23: 2027 | C23: 2028 | D23: 2029 | E23: 2030 | F23: 2031 | G23: 2032 | H23: 2033 | I23: 2034 | J23: 2035 | K23: 2036
A24: Net Ticket Revenue (adj.) | B24: ='P&L'!B10*$B$60*$B$61 | C24: ='P&L'!C10*$B$60*$B$61 | D24: ='P&L'!D10*$B$60*$B$61 | E24: ='P&L'!E10*$B$60*$B$61 | F24: ='P&L'!F10*$B$60*$B$61 | G24: ='P&L'!G10*$B$60*$B$61 | H24: ='P&L'!H10*$B$60*$B$61 | I24: ='P&L'!I10*$B$60*$B$61 | ... K24: ='P&L'!K10*$B$60*$B$61
A25: Partnership Revenue (adj.) | B25: ='P&L'!B11*$B$62 | C25: ='P&L'!C11*$B$62 | D25: ='P&L'!D11*$B$62 | E25: ='P&L'!E11*$B$62 | F25: ='P&L'!F11*$B$62 | G25: ='P&L'!G11*$B$62 | H25: ='P&L'!H11*$B$62 | I25: ='P&L'!I11*$B$62 | ... K25: ='P&L'!K11*$B$62
A26: Other Revenue (ASA+F&B+Dinner+Other) (adj.) | B26: ='P&L'!B12*$B$63+'P&L'!B13+'P&L'!B14+'P&L'!B15 | C26: ='P&L'!C12*$B$63+'P&L'!C13+'P&L'!C14+'P&L'!C15 | D26: ='P&L'!D12*$B$63+'P&L'!D13+'P&L'!D14+'P&L'!D15 | E26: ='P&L'!E12*$B$63+'P&L'!E13+'P&L'!E14+'P&L'!E15 | F26: ='P&L'!F12*$B$63+'P&L'!F13+'P&L'!F14+'P&L'!F15 | G26: ='P&L'!G12*$B$63+'P&L'!G13+'P&L'!G14+'P&L'!G15 | H26: ='P&L'!H12*$B$63+'P&L'!H13+'P&L'!H14+'P&L'!H15 | I26: ='P&L'!I12*$B$63+'P&L'!I13+'P&L'!I14+'P&L'!I15 | ... K26: ='P&L'!K12*$B$63+'P&L'!K13+'P&L'!K14+'P&L'!K15
A27: Total Revenue | B27: =(B24+B25+B26)*(1+IF(2027>=$B$71,Revenue!$B$11,0)) | C27: =(C24+C25+C26)*(1+IF(2028>=$B$71,Revenue!$B$11,0)) | D27: =(D24+D25+D26)*(1+IF(2029>=$B$71,Revenue!$B$11,0)) | E27: =(E24+E25+E26)*(1+IF(2030>=$B$71,Revenue!$B$11,0)) | F27: =(F24+F25+F26)*(1+IF(2031>=$B$71,Revenue!$B$11,0)) | G27: =(G24+G25+G26)*(1+IF(2032>=$B$71,Revenue!$B$11,0)) | H27: =(H24+H25+H26)*(1+IF(2033>=$B$71,Revenue!$B$11,0)) | I27: =(I24+I25+I26)*(1+IF(2034>=$B$71,Revenue!$B$11,0)) | J27: =(J24+J25+J26)*(1+IF(2035>=$B$71,Revenue!$B$11,0)) | K27: =(K24+K25+K26)*(1+IF(2036>=$B$71,Revenue!$B$11,0))
A28: Total Costs (adj.) | B28: ='P&L'!B20*$B$66-$B$68+'P&L'!B22*$B$67 | C28: ='P&L'!C20*$B$66-$B$68+'P&L'!C22*$B$67 | D28: ='P&L'!D20*$B$66-$B$68+'P&L'!D22*$B$67 | E28: ='P&L'!E20*$B$66-$B$68+'P&L'!E22*$B$67 | F28: ='P&L'!F20*$B$66-$B$68+'P&L'!F22*$B$67 | G28: ='P&L'!G20*$B$66-$B$68+'P&L'!G22*$B$67 | H28: ='P&L'!H20*$B$66-$B$68+'P&L'!H22*$B$67 | I28: ='P&L'!I20*$B$66-$B$68+'P&L'!I22*$B$67 | ... K28: ='P&L'!K20*$B$66-$B$68+'P&L'!K22*$B$67
A29: EBIT | B29: =B27+B28 | C29: =C27+C28 | D29: =D27+D28 | E29: =E27+E28 | F29: =F27+F28 | G29: =G27+G28 | H29: =H27+H28 | I29: =I27+I28 | ... K29: =K27+K28
A30: Tax | B30: =IF(B29>0,-B29*'P&L'!$B$5,0) | C30: =IF(C29>0,-C29*'P&L'!$B$5,0) | D30: =IF(D29>0,-D29*'P&L'!$B$5,0) | E30: =IF(E29>0,-E29*'P&L'!$B$5,0) | F30: =IF(F29>0,-F29*'P&L'!$B$5,0) | G30: =IF(G29>0,-G29*'P&L'!$B$5,0) | H30: =IF(H29>0,-H29*'P&L'!$B$5,0) | I30: =IF(I29>0,-I29*'P&L'!$B$5,0) | ... K30: =IF(K29>0,-K29*'P&L'!$B$5,0)
A31: Profit After Tax | B31: =B29+B30 | C31: =C29+C30 | D31: =D29+D30 | E31: =E29+E30 | F31: =F29+F30 | G31: =G29+G30 | H31: =H29+H30 | I31: =I29+I30 | ... K31: =K29+K30
A32: Cumulative Cash | B32: ='P&L'!$B$6+B31 | C32: =B32+C31 | D32: =C32+D31 | E32: =D32+E31 | F32: =E32+F31 | G32: =F32+G31 | H32: =G32+H31 | I32: =H32+I31 | J32: =I32+J31 | K32: =J32+K31
A34: UPSIDE SCENARIO
B35: 2027 | C35: 2028 | D35: 2029 | E35: 2030 | F35: 2031 | G35: 2032 | H35: 2033 | I35: 2034 | J35: 2035 | K35: 2036
A36: Net Ticket Revenue (adj.) | B36: ='P&L'!B10*$D$60*$D$61 | C36: ='P&L'!C10*$D$60*$D$61 | D36: ='P&L'!D10*$D$60*$D$61 | E36: ='P&L'!E10*$D$60*$D$61 | F36: ='P&L'!F10*$D$60*$D$61 | G36: ='P&L'!G10*$D$60*$D$61 | H36: ='P&L'!H10*$D$60*$D$61 | I36: ='P&L'!I10*$D$60*$D$61 | ... K36: ='P&L'!K10*$D$60*$D$61
A37: Partnership Revenue (adj.) | B37: ='P&L'!B11*$D$62 | C37: ='P&L'!C11*$D$62 | D37: ='P&L'!D11*$D$62 | E37: ='P&L'!E11*$D$62 | F37: ='P&L'!F11*$D$62 | G37: ='P&L'!G11*$D$62 | H37: ='P&L'!H11*$D$62 | I37: ='P&L'!I11*$D$62 | ... K37: ='P&L'!K11*$D$62
A38: Other Revenue (ASA+F&B+Dinner+Other) (adj.) | B38: ='P&L'!B12*$D$63+'P&L'!B13+'P&L'!B14+'P&L'!B15 | C38: ='P&L'!C12*$D$63+'P&L'!C13+'P&L'!C14+'P&L'!C15 | D38: ='P&L'!D12*$D$63+'P&L'!D13+'P&L'!D14+'P&L'!D15 | E38: ='P&L'!E12*$D$63+'P&L'!E13+'P&L'!E14+'P&L'!E15 | F38: ='P&L'!F12*$D$63+'P&L'!F13+'P&L'!F14+'P&L'!F15 | G38: ='P&L'!G12*$D$63+'P&L'!G13+'P&L'!G14+'P&L'!G15 | H38: ='P&L'!H12*$D$63+'P&L'!H13+'P&L'!H14+'P&L'!H15 | I38: ='P&L'!I12*$D$63+'P&L'!I13+'P&L'!I14+'P&L'!I15 | ... K38: ='P&L'!K12*$D$63+'P&L'!K13+'P&L'!K14+'P&L'!K15
A39: Total Revenue | B39: =(B36+B37+B38)*(1+IF(2027>=$D$71,Revenue!$B$11,0)) | C39: =(C36+C37+C38)*(1+IF(2028>=$D$71,Revenue!$B$11,0)) | D39: =(D36+D37+D38)*(1+IF(2029>=$D$71,Revenue!$B$11,0)) | E39: =(E36+E37+E38)*(1+IF(2030>=$D$71,Revenue!$B$11,0)) | F39: =(F36+F37+F38)*(1+IF(2031>=$D$71,Revenue!$B$11,0)) | G39: =(G36+G37+G38)*(1+IF(2032>=$D$71,Revenue!$B$11,0)) | H39: =(H36+H37+H38)*(1+IF(2033>=$D$71,Revenue!$B$11,0)) | I39: =(I36+I37+I38)*(1+IF(2034>=$D$71,Revenue!$B$11,0)) | J39: =(J36+J37+J38)*(1+IF(2035>=$D$71,Revenue!$B$11,0)) | K39: =(K36+K37+K38)*(1+IF(2036>=$D$71,Revenue!$B$11,0))
A40: Total Costs (adj.) | B40: ='P&L'!B20*$D$66+'P&L'!B21+'P&L'!B22*$D$67 | C40: ='P&L'!C20*$D$66+'P&L'!C21+'P&L'!C22*$D$67 | D40: ='P&L'!D20*$D$66+'P&L'!D21+'P&L'!D22*$D$67 | E40: ='P&L'!E20*$D$66+'P&L'!E21+'P&L'!E22*$D$67 | F40: ='P&L'!F20*$D$66+'P&L'!F21+'P&L'!F22*$D$67 | G40: ='P&L'!G20*$D$66+'P&L'!G21+'P&L'!G22*$D$67 | H40: ='P&L'!H20*$D$66+'P&L'!H21+'P&L'!H22*$D$67 | I40: ='P&L'!I20*$D$66+'P&L'!I21+'P&L'!I22*$D$67 | ... K40: ='P&L'!K20*$D$66+'P&L'!K21+'P&L'!K22*$D$67
A41: EBIT | B41: =B39+B40 | C41: =C39+C40 | D41: =D39+D40 | E41: =E39+E40 | F41: =F39+F40 | G41: =G39+G40 | H41: =H39+H40 | I41: =I39+I40 | ... K41: =K39+K40
A42: Tax | B42: =IF(B41>0,-B41*'P&L'!$B$5,0) | C42: =IF(C41>0,-C41*'P&L'!$B$5,0) | D42: =IF(D41>0,-D41*'P&L'!$B$5,0) | E42: =IF(E41>0,-E41*'P&L'!$B$5,0) | F42: =IF(F41>0,-F41*'P&L'!$B$5,0) | G42: =IF(G41>0,-G41*'P&L'!$B$5,0) | H42: =IF(H41>0,-H41*'P&L'!$B$5,0) | I42: =IF(I41>0,-I41*'P&L'!$B$5,0) | ... K42: =IF(K41>0,-K41*'P&L'!$B$5,0)
A43: Profit After Tax | B43: =B41+B42 | C43: =C41+C42 | D43: =D41+D42 | E43: =E41+E42 | F43: =F41+F42 | G43: =G41+G42 | H43: =H41+H42 | I43: =I41+I42 | ... K43: =K41+K42
A44: Cumulative Cash | B44: ='P&L'!$B$6+B43 | C44: =B44+C43 | D44: =C44+D43 | E44: =D44+E43 | F44: =E44+F43 | G44: =F44+G43 | H44: =G44+H43 | I44: =H44+I43 | J44: =I44+J43 | K44: =J44+K43
A55: SCENARIO ADJUSTMENTS (change values below to adjust scenarios)
B56: Downside | C56: Base | D56: Upside
A58: ■ REVENUE FACTORS
A59: These multiply each year's revenue line directly.
A60: Ticket Occupancy | B60: 0.85 | C60: 1 | D60: 1
A61: Ticket Price Factor | B61: 0.9 | C61: 1 | D61: 1.1
A62: Partnership Factor | B62: 0.6 | C62: 1 | D62: 1.4
A63: ASA Factor | B63: 0.75 | C63: 1 | D63: 1.25
A65: ■ COST FACTORS
A66: Direct Cost Factor | B66: 0.8 | C66: 1 | D66: 1
A67: Founder Pay Factor | B67: 0.5 | C67: 1 | D67: 1
A68: Downside Overhead (CHF) | B68: 8000
A70: ■ STRUCTURAL FACTORS
A71: Summer Start Year | B71: 2029 | C71: 2027 | D71: 2027
A73: SCENARIO DEFINITIONS:
A74: Downside: Tickets -15%, prices -10%, partnerships -40%, ASA -25%, direct costs ×0.8, overhead fixed 8K, founder pay halved, summer from 2029.
A75: Base: All factors at 1.0 — as entered in Revenue/Cost sheets. Summer from 2027.
A76: Upside: Prices +10%, partnerships +40%, ASA +25%. Summer from 2027.

Sheet Revenue
A1: REVENUE
A3: MODEL ASSUMPTIONS
A4: Total Guest Count | B4: 280
A5: Total Ticket Count | B5: 250
A6: Net Factor (VAT + platform fees) | B6: 0.89
A7: Ticket Price Growth Rate (to 2030) | B7: 0.08
A8: Ticket Price Growth Rate (2031+) | B8: 0.04
A9: F&B Growth Rate | B9: 0.03
A10: Partnership Growth Rate (2032+) | B10: 0.06
A11: Summer Revenue Multiplier | B11: 0.55
A12: Summer Cost Multiplier | B12: 0.5
A13: Summer Start Year | B13: 2027
A15: SECTION 1: TICKET REVENUE
A16: Drop Allocation
A17: Drop 1 Allocation % | B17: 0.28
A18: Drop 2 Allocation % | B18: 0.44
A19: Drop 3 Allocation % | B19: 0.28
A21: 2027 Base Prices (CHF)
A22: Drop 1 Unit Price | B22: 210
A23: Drop 2 Unit Price | B23: 250
A24: Drop 3 Unit Price | B24: 290
A26: 10-YEAR TICKET PROJECTION
B27: 2027 | C27: 2028 | D27: 2029 | E27: 2030 | F27: 2031 | G27: 2032 | H27: 2033 | I27: 2034 | J27: 2035 | K27: 2036
A28: Drop 1 Quantity | B28: =ROUND($B$5*$B$17,0) | C28: =ROUND($B$5*$B$17,0) | D28: =ROUND($B$5*$B$17,0) | E28: =ROUND($B$5*$B$17,0) | F28: =ROUND($B$5*$B$17,0) | G28: =ROUND($B$5*$B$17,0) | H28: =ROUND($B$5*$B$17,0) | I28: =ROUND($B$5*$B$17,0) | ... K28: =ROUND($B$5*$B$17,0)
A29: Drop 2 Quantity | B29: =ROUND($B$5*$B$18,0) | C29: =ROUND($B$5*$B$18,0) | D29: =ROUND($B$5*$B$18,0) | E29: =ROUND($B$5*$B$18,0) | F29: =ROUND($B$5*$B$18,0) | G29: =ROUND($B$5*$B$18,0) | H29: =ROUND($B$5*$B$18,0) | I29: =ROUND($B$5*$B$18,0) | ... K29: =ROUND($B$5*$B$18,0)
A30: Drop 3 Quantity | B30: =ROUND($B$5*$B$19,0) | C30: =ROUND($B$5*$B$19,0) | D30: =ROUND($B$5*$B$19,0) | E30: =ROUND($B$5*$B$19,0) | F30: =ROUND($B$5*$B$19,0) | G30: =ROUND($B$5*$B$19,0) | H30: =ROUND($B$5*$B$19,0) | I30: =ROUND($B$5*$B$19,0) | ... K30: =ROUND($B$5*$B$19,0)
A32: Drop 1 Price (CHF) | B32: =$B$22 | C32: =IF(2028<=2030,B32*(1+$B$7),B32*(1+$B$8)) | D32: =IF(2029<=2030,C32*(1+$B$7),C32*(1+$B$8)) | E32: =IF(2030<=2030,D32*(1+$B$7),D32*(1+$B$8)) | F32: =IF(2031<=2030,E32*(1+$B$7),E32*(1+$B$8)) | G32: =IF(2032<=2030,F32*(1+$B$7),F32*(1+$B$8)) | H32: =IF(2033<=2030,G32*(1+$B$7),G32*(1+$B$8)) | I32: =IF(2034<=2030,H32*(1+$B$7),H32*(1+$B$8)) | J32: =IF(2035<=2030,I32*(1+$B$7),I32*(1+$B$8)) | K32: =IF(2036<=2030,J32*(1+$B$7),J32*(1+$B$8))
A33: Drop 2 Price (CHF) | B33: =$B$23 | C33: =IF(2028<=2030,B33*(1+$B$7),B33*(1+$B$8)) | D33: =IF(2029<=2030,C33*(1+$B$7),C33*(1+$B$8)) | E33: =IF(2030<=2030,D33*(1+$B$7),D33*(1+$B$8)) | F33: =IF(2031<=2030,E33*(1+$B$7),E33*(1+$B$8)) | G33: =IF(2032<=2030,F33*(1+$B$7),F33*(1+$B$8)) | H33: =IF(2033<=2030,G33*(1+$B$7),G33*(1+$B$8)) | I33: =IF(2034<=2030,H33*(1+$B$7),H33*(1+$B$8)) | J33: =IF(2035<=2030,I33*(1+$B$7),I33*(1+$B$8)) | K33: =IF(2036<=2030,J33*(1+$B$7),J33*(1+$B$8))
A34: Drop 3 Price (CHF) | B34: =$B$24 | C34: =IF(2028<=2030,B34*(1+$B$7),B34*(1+$B$8)) | D34: =IF(2029<=2030,C34*(1+$B$7),C34*(1+$B$8)) | E34: =IF(2030<=2030,D34*(1+$B$7),D34*(1+$B$8)) | F34: =IF(2031<=2030,E34*(1+$B$7),E34*(1+$B$8)) | G34: =IF(2032<=2030,F34*(1+$B$7),F34*(1+$B$8)) | H34: =IF(2033<=2030,G34*(1+$B$7),G34*(1+$B$8)) | I34: =IF(2034<=2030,H34*(1+$B$7),H34*(1+$B$8)) | J34: =IF(2035<=2030,I34*(1+$B$7),I34*(1+$B$8)) | K34: =IF(2036<=2030,J34*(1+$B$7),J34*(1+$B$8))
A36: Drop 1 Revenue | B36: =B28*B32 | C36: =C28*C32 | D36: =D28*D32 | E36: =E28*E32 | F36: =F28*F32 | G36: =G28*G32 | H36: =H28*H32 | I36: =I28*I32 | ... K36: =K28*K32
A37: Drop 2 Revenue | B37: =B29*B33 | C37: =C29*C33 | D37: =D29*D33 | E37: =E29*E33 | F37: =F29*F33 | G37: =G29*G33 | H37: =H29*H33 | I37: =I29*I33 | ... K37: =K29*K33
A38: Drop 3 Revenue | B38: =B30*B34 | C38: =C30*C34 | D38: =D30*D34 | E38: =E30*E34 | F38: =F30*F34 | G38: =G30*G34 | H38: =H30*H34 | I38: =I30*I34 | ... K38: =K30*K34
A39: Gross Ticket Revenue | B39: =B36+B37+B38 | C39: =C36+C37+C38 | D39: =D36+D37+D38 | E39: =E36+E37+E38 | F39: =F36+F37+F38 | G39: =G36+G37+G38 | H39: =H36+H37+H38 | I39: =I36+I37+I38 | ... K39: =K36+K37+K38
A40: Net Ticket Revenue | B40: =B39*$B$6 | C40: =C39*$B$6 | D40: =D39*$B$6 | E40: =E39*$B$6 | F40: =F39*$B$6 | G40: =G39*$B$6 | H40: =H39*$B$6 | I40: =I39*$B$6 | ... K40: =K39*$B$6
A42: SECTION 2: PARTNERSHIPS
B43: 2027 | C43: 2028 | D43: 2029 | E43: 2030 | F43: 2031 | G43: 2032 | H43: 2033 | I43: 2034 | J43: 2035 | K43: 2036
A44: Presenting Partner — Price | B44: 0 | C44: 50000 | D44: 50000 | E44: 50000 | F44: 50000
A45: Presenting Partner — Count | B45: 0 | C45: 1 | D45: 1 | E45: 1 | F45: 1
A46: Presenting Partner — Revenue | B46: =B44*B45 | C46: =C44*C45 | D46: =D44*D45 | E46: =E44*E45 | F46: =F44*F45
A48: Partner — Price | B48: 15000 | C48: 0 | D48: 15000 | E48: 15000 | F48: 15000
A49: Partner — Count | B49: 2 | C49: 0 | D49: 1 | E49: 2 | F49: 3
A50: Partner — Revenue | B50: =B48*B49 | C50: =C48*C49 | D50: =D48*D49 | E50: =E48*E49 | F50: =F48*F49
A52: Supporting Partner — Price | B52: 0 | C52: 5000 | D52: 5000 | E52: 5000 | F52: 5000
A53: Supporting Partner — Count | B53: 0 | C53: 1 | D53: 2 | E53: 3 | F53: 3
A54: Supporting Partner — Revenue | B54: =B52*B53 | C54: =C52*C53 | D54: =D52*D53 | E54: =E52*E53 | F54: =F52*F53
A56: Partnership Total | B56: =B46+B50+B54 | C56: =C46+C50+C54 | D56: =D46+D50+D54 | E56: =E46+E50+E54 | F56: =F46+F50+F54 | G56: =F56*(1+$B$10)^1 | H56: =F56*(1+$B$10)^2 | I56: =F56*(1+$B$10)^3 | J56: =F56*(1+$B$10)^4 | K56: =F56*(1+$B$10)^5
A57: 2027-2031: Tier breakdown (editable). 2032-2036: Auto-calculated from 2031 total at Partnership Growth Rate.
A59: SECTION 3: ASA CONTRIBUTION
B60: 2027 | C60: 2028 | D60: 2029 | E60: 2030 | F60: 2031 | G60: 2032 | H60: 2033 | I60: 2034 | J60: 2035 | K60: 2036
A61: ASA Contribution (manual input) | B61: 10000 | C61: 12500 | D61: 15000 | E61: 20000 | F61: 25000 | G61: 30000 | H61: 30000 | I61: 35000 | J61: 40000 | K61: 45000
A62: ASA partnership contribution follows a 3-phase negotiation schedule (Build / Grow / Anchor). Values are irregular and entered manually per year.
A64: SECTION 4: BAR / F&B REVENUE
A65: Share rates are currently set to 0%. Aura does not take a share of bar/food revenue. If a share agreement is negotiated, change the share rate.
B67: 2027 | C67: 2028 | D67: 2029 | E67: 2030 | F67: 2031 | G67: 2032 | H67: 2033 | I67: 2034 | J67: 2035 | K67: 2036
A68: Friday Night: Coffee + Drinks — Guest Count | B68: 150
A69: Friday Night: Coffee + Drinks — Per-person Spend | B69: 50
A70: Friday Night: Coffee + Drinks — Share Rate | B70: 0
A71: Friday Night: Coffee + Drinks — Est. Total Sales (reference) | B71: =B68*B69 | C71: =B71*(1+$B$9) | D71: =C71*(1+$B$9) | E71: =D71*(1+$B$9) | F71: =E71*(1+$B$9) | G71: =F71*(1+$B$9) | H71: =G71*(1+$B$9) | I71: =H71*(1+$B$9) | J71: =I71*(1+$B$9) | K71: =J71*(1+$B$9)
A72: Friday Night: Coffee + Drinks — Aura Revenue | B72: =B71*$B70 | C72: =C71*$B70 | D72: =D71*$B70 | E72: =E71*$B70 | F72: =F71*$B70 | G72: =G71*$B70 | H72: =H71*$B70 | I72: =I71*$B70 | ... K72: =K71*$B70
A74: Saturday Day: Drinks — Guest Count | B74: 280
A75: Saturday Day: Drinks — Per-person Spend | B75: 20
A76: Saturday Day: Drinks — Share Rate | B76: 0
A77: Saturday Day: Drinks — Est. Total Sales (reference) | B77: =B74*B75 | C77: =B77*(1+$B$9) | D77: =C77*(1+$B$9) | E77: =D77*(1+$B$9) | F77: =E77*(1+$B$9) | G77: =F77*(1+$B$9) | H77: =G77*(1+$B$9) | I77: =H77*(1+$B$9) | J77: =I77*(1+$B$9) | K77: =J77*(1+$B$9)
A78: Saturday Day: Drinks — Aura Revenue | B78: =B77*$B76 | C78: =C77*$B76 | D78: =D77*$B76 | E78: =E77*$B76 | F78: =F77*$B76 | G78: =G77*$B76 | H78: =H77*$B76 | I78: =I77*$B76 | ... K78: =K77*$B76
A80: Saturday Day: Food — Guest Count | B80: 280
A81: Saturday Day: Food — Per-person Spend | B81: 50
A82: Saturday Day: Food — Share Rate | B82: 0
A83: Saturday Day: Food — Est. Total Sales (reference) | B83: =B80*B81 | C83: =B83*(1+$B$9) | D83: =C83*(1+$B$9) | E83: =D83*(1+$B$9) | F83: =E83*(1+$B$9) | G83: =F83*(1+$B$9) | H83: =G83*(1+$B$9) | I83: =H83*(1+$B$9) | J83: =I83*(1+$B$9) | K83: =J83*(1+$B$9)
A84: Saturday Day: Food — Aura Revenue | B84: =B83*$B82 | C84: =C83*$B82 | D84: =D83*$B82 | E84: =E83*$B82 | F84: =F83*$B82 | G84: =G83*$B82 | H84: =H83*$B82 | I84: =I83*$B82 | ... K84: =K83*$B82
A86: Saturday Night: Drinks — Guest Count | B86: 150
A87: Saturday Night: Drinks — Per-person Spend | B87: 50
A88: Saturday Night: Drinks — Share Rate | B88: 0
A89: Saturday Night: Drinks — Est. Total Sales (reference) | B89: =B86*B87 | C89: =B89*(1+$B$9) | D89: =C89*(1+$B$9) | E89: =D89*(1+$B$9) | F89: =E89*(1+$B$9) | G89: =F89*(1+$B$9) | H89: =G89*(1+$B$9) | I89: =H89*(1+$B$9) | J89: =I89*(1+$B$9) | K89: =J89*(1+$B$9)
A90: Saturday Night: Drinks — Aura Revenue | B90: =B89*$B88 | C90: =C89*$B88 | D90: =D89*$B88 | E90: =E89*$B88 | F90: =F89*$B88 | G90: =G89*$B88 | H90: =H89*$B88 | I90: =I89*$B88 | ... K90: =K89*$B88
A92: Sunday Coffee — Guest Count | B92: 80
A93: Sunday Coffee — Per-person Spend | B93: 8
A94: Sunday Coffee — Share Rate | B94: 0
A95: Sunday Coffee — Est. Total Sales (reference) | B95: =B92*B93 | C95: =B95*(1+$B$9) | D95: =C95*(1+$B$9) | E95: =D95*(1+$B$9) | F95: =E95*(1+$B$9) | G95: =F95*(1+$B$9) | H95: =G95*(1+$B$9) | I95: =H95*(1+$B$9) | J95: =I95*(1+$B$9) | K95: =J95*(1+$B$9)
A96: Sunday Coffee — Aura Revenue | B96: =B95*$B94 | C96: =C95*$B94 | D96: =D95*$B94 | E96: =E95*$B94 | F96: =F95*$B94 | G96: =G95*$B94 | H96: =H95*$B94 | I96: =I95*$B94 | ... K96: =K95*$B94
A98: Bar/F&B Total | B98: =B72+B78+B84+B90+B96 | C98: =C72+C78+C84+C90+C96 | D98: =D72+D78+D84+D90+D96 | E98: =E72+E78+E84+E90+E96 | F98: =F72+F78+F84+F90+F96 | G98: =G72+G78+G84+G90+G96 | H98: =H72+H78+H84+H90+H96 | I98: =I72+I78+I84+I90+I96 | ... K98: =K72+K78+K84+K90+K96
A100: SECTION 5: DINNER REVENUE
B101: 2027 | C101: 2028 | D101: 2029 | E101: 2030 | F101: 2031 | G101: 2032 | H101: 2033 | I101: 2034 | J101: 2035 | K101: 2036
A102: Dinner Revenue (manual input) | B102: 0 | C102: 0 | D102: 0 | E102: 0 | F102: 0 | G102: 0 | H102: 0 | I102: 0 | J102: 0 | K102: 0
A103: BP: 'Dinner is invite-only, sponsor-funded, never sold.' If a dinner-specific sponsor appears, it goes under Partnerships.
A105: SECTION 6: OTHER REVENUE
B106: 2027 | C106: 2028 | D106: 2029 | E106: 2030 | F106: 2031 | G106: 2032 | H106: 2033 | I106: 2034 | J106: 2035 | K106: 2036
A107: Other Revenue | B107: 2000 | C107: =B107*(1+'P&L'!$B$4) | D107: =C107*(1+'P&L'!$B$4) | E107: =D107*(1+'P&L'!$B$4) | F107: =E107*(1+'P&L'!$B$4) | G107: =F107*(1+'P&L'!$B$4) | H107: =G107*(1+'P&L'!$B$4) | I107: =H107*(1+'P&L'!$B$4) | J107: =I107*(1+'P&L'!$B$4) | K107: =J107*(1+'P&L'!$B$4)
A108: Other Revenue grows with General Inflation Rate (P&L sheet). Contents: add-ons, upselling, merchandise.
A110: REVENUE TOTALS
B111: 2027 | C111: 2028 | D111: 2029 | E111: 2030 | F111: 2031 | G111: 2032 | H111: 2033 | I111: 2034 | J111: 2035 | K111: 2036
A112: TOTAL WINTER REVENUE | B112: =B40+B56+B61+B98+B102+B107 | C112: =C40+C56+C61+C98+C102+C107 | D112: =D40+D56+D61+D98+D102+D107 | E112: =E40+E56+E61+E98+E102+E107 | F112: =F40+F56+F61+F98+F102+F107 | G112: =G40+G56+G61+G98+G102+G107 | H112: =H40+H56+H61+H98+H102+H107 | I112: =I40+I56+I61+I98+I102+I107 | ... K112: =K40+K56+K61+K98+K102+K107
A113: Summer Revenue | B113: =IF(2027>=$B$13,B112*$B$11,0) | C113: =IF(2028>=$B$13,C112*$B$11,0) | D113: =IF(2029>=$B$13,D112*$B$11,0) | E113: =IF(2030>=$B$13,E112*$B$11,0) | F113: =IF(2031>=$B$13,F112*$B$11,0) | G113: =IF(2032>=$B$13,G112*$B$11,0) | H113: =IF(2033>=$B$13,H112*$B$11,0) | I113: =IF(2034>=$B$13,I112*$B$11,0) | J113: =IF(2035>=$B$13,J112*$B$11,0) | K113: =IF(2036>=$B$13,K112*$B$11,0)
A114: TOTAL ANNUAL REVENUE | B114: =B112+B113 | C114: =C112+C113 | D114: =D112+D113 | E114: =E112+E113 | F114: =F112+F113 | G114: =G112+G113 | H114: =H112+H113 | I114: =I112+I113 | ... K114: =K112+K113

Sheet P&L
A1: PROFIT & LOSS
A3: EXTERNAL PARAMETERS (normally do not change)
A4: General Inflation Rate | B4: 0.02
A5: Tax Rate (Uri canton combined) | B5: 0.1264
A6: Initial Capital (GmbH paid-in) | B6: 20000
A8: 10-YEAR PROFIT & LOSS
B9: 2027 | C9: 2028 | D9: 2029 | E9: 2030 | F9: 2031 | G9: 2032 | H9: 2033 | I9: 2034 | J9: 2035 | K9: 2036
A10: Net Ticket Revenue | B10: =Revenue!B40 | C10: =Revenue!C40 | D10: =Revenue!D40 | E10: =Revenue!E40 | F10: =Revenue!F40 | G10: =Revenue!G40 | H10: =Revenue!H40 | I10: =Revenue!I40 | ... K10: =Revenue!K40
A11: Partnership Revenue | B11: =Revenue!B56 | C11: =Revenue!C56 | D11: =Revenue!D56 | E11: =Revenue!E56 | F11: =Revenue!F56 | G11: =Revenue!G56 | H11: =Revenue!H56 | I11: =Revenue!I56 | ... K11: =Revenue!K56
A12: ASA Contribution | B12: =Revenue!B61 | C12: =Revenue!C61 | D12: =Revenue!D61 | E12: =Revenue!E61 | F12: =Revenue!F61 | G12: =Revenue!G61 | H12: =Revenue!H61 | I12: =Revenue!I61 | ... K12: =Revenue!K61
A13: Bar/F&B Revenue | B13: =Revenue!B98 | C13: =Revenue!C98 | D13: =Revenue!D98 | E13: =Revenue!E98 | F13: =Revenue!F98 | G13: =Revenue!G98 | H13: =Revenue!H98 | I13: =Revenue!I98 | ... K13: =Revenue!K98
A14: Dinner Revenue | B14: =Revenue!B102 | C14: =Revenue!C102 | D14: =Revenue!D102 | E14: =Revenue!E102 | F14: =Revenue!F102 | G14: =Revenue!G102 | H14: =Revenue!H102 | I14: =Revenue!I102 | ... K14: =Revenue!K102
A15: Other Revenue | B15: =Revenue!B107 | C15: =Revenue!C107 | D15: =Revenue!D107 | E15: =Revenue!E107 | F15: =Revenue!F107 | G15: =Revenue!G107 | H15: =Revenue!H107 | I15: =Revenue!I107 | ... K15: =Revenue!K107
A17: TOTAL REVENUE | B17: =Revenue!B114 | C17: =Revenue!C114 | D17: =Revenue!D114 | E17: =Revenue!E114 | F17: =Revenue!F114 | G17: =Revenue!G114 | H17: =Revenue!H114 | I17: =Revenue!I114 | ... K17: =Revenue!K114
A19: Costs
A20: Total Direct Costs | B20: =-Cost!B49 | C20: =-Cost!C49 | D20: =-Cost!D49 | E20: =-Cost!E49 | F20: =-Cost!F49 | G20: =-Cost!G49 | H20: =-Cost!H49 | I20: =-Cost!I49 | ... K20: =-Cost!K49
A21: Overhead | B21: =-Cost!B53 | C21: =-Cost!C53 | D21: =-Cost!D53 | E21: =-Cost!E53 | F21: =-Cost!F53 | G21: =-Cost!G53 | H21: =-Cost!H53 | I21: =-Cost!I53 | ... K21: =-Cost!K53
A22: Founder Pay | B22: =-Cost!B55 | C22: =-Cost!C55 | D22: =-Cost!D55 | E22: =-Cost!E55 | F22: =-Cost!F55 | G22: =-Cost!G55 | H22: =-Cost!H55 | I22: =-Cost!I55 | ... K22: =-Cost!K55
A24: TOTAL COSTS | B24: =B20+B21+B22 | C24: =C20+C21+C22 | D24: =D20+D21+D22 | E24: =E20+E21+E22 | F24: =F20+F21+F22 | G24: =G20+G21+G22 | H24: =H20+H21+H22 | I24: =I20+I21+I22 | ... K24: =K20+K21+K22
A26: RESULTS
A27: EBIT | B27: =B17+B24 | C27: =C17+C24 | D27: =D17+D24 | E27: =E17+E24 | F27: =F17+F24 | G27: =G17+G24 | H27: =H17+H24 | I27: =I17+I24 | ... K27: =K17+K24
A28: Tax | B28: =IF(B27>0,-B27*$B$5,0) | C28: =IF(C27>0,-C27*$B$5,0) | D28: =IF(D27>0,-D27*$B$5,0) | E28: =IF(E27>0,-E27*$B$5,0) | F28: =IF(F27>0,-F27*$B$5,0) | G28: =IF(G27>0,-G27*$B$5,0) | H28: =IF(H27>0,-H27*$B$5,0) | I28: =IF(I27>0,-I27*$B$5,0) | ... K28: =IF(K27>0,-K27*$B$5,0)
A29: PROFIT AFTER TAX | B29: =B27+B28 | C29: =C27+C28 | D29: =D27+D28 | E29: =E27+E28 | F29: =F27+F28 | G29: =G27+G28 | H29: =H27+H28 | I29: =I27+I28 | ... K29: =K27+K28
A30: CUMULATIVE CASH | B30: =$B$6+B29 | C30: =B30+C29 | D30: =C30+D29 | E30: =D30+E29 | F30: =E30+F29 | G30: =F30+G29 | H30: =G30+H29 | I30: =H30+I29 | J30: =I30+J29 | K30: =J30+K29

Sheet Cost
A1: COST
A3: MODEL ASSUMPTIONS
A4: Venue Contract Escalation Rate | B4: 0.03
A5: Ambition Growth Rate (Category C) | B5: 0.06
A6: Contingency % | B6: 0.09
A8: COST CATEGORY DEFINITIONS:
A9: Category A (Fixed/Contract): Costs driven by contracts or predictable obligations. Grow at contractual rate or general inflation.
A10: Category B (Guest-linked): Costs that scale with the number of ticket holders. More tickets sold = higher cost.
A11: Category C (Ambition-linked): Costs tied to the quality and ambition of the event. Default growth: Ambition Growth Rate above.
A12: Contingency: A buffer calculated as % of total costs (A+B+C) for unexpected expenses.
A14: CATEGORY A: FIXED / CONTRACT
B15: 2027 | C15: 2028 | D15: 2029 | E15: 2030 | F15: 2031 | G15: 2032 | H15: 2033 | I15: 2034 | J15: 2035 | K15: 2036
A16: Venue (Swiss House) | B16: 27951 | C16: =B16*(1+$B$4) | D16: =C16*(1+$B$4) | E16: =D16*(1+$B$4) | F16: =E16*(1+$B$4) | G16: =F16*(1+$B$4) | H16: =G16*(1+$B$4) | I16: =H16*(1+$B$4) | J16: =I16*(1+$B$4) | K16: =J16*(1+$B$4)
A17: F&B Credit (guest spend vs minimums) | B17: -9000 | C17: =B17*(1+$B$4) | D17: =C17*(1+$B$4) | E17: =D17*(1+$B$4) | F17: =E17*(1+$B$4) | G17: =F17*(1+$B$4) | H17: =G17*(1+$B$4) | I17: =H17*(1+$B$4) | J17: =I17*(1+$B$4) | K17: =J17*(1+$B$4)
A18: Insurance / Permits / Ticketing | B18: 2500 | C18: =B18*(1+'P&L'!$B$4) | D18: =C18*(1+'P&L'!$B$4) | E18: =D18*(1+'P&L'!$B$4) | F18: =E18*(1+'P&L'!$B$4) | G18: =F18*(1+'P&L'!$B$4) | H18: =G18*(1+'P&L'!$B$4) | I18: =H18*(1+'P&L'!$B$4) | J18: =I18*(1+'P&L'!$B$4) | K18: =J18*(1+'P&L'!$B$4)
A19: Transport | B19: 2500 | C19: =B19*(1+'P&L'!$B$4) | D19: =C19*(1+'P&L'!$B$4) | E19: =D19*(1+'P&L'!$B$4) | F19: =E19*(1+'P&L'!$B$4) | G19: =F19*(1+'P&L'!$B$4) | H19: =G19*(1+'P&L'!$B$4) | I19: =H19*(1+'P&L'!$B$4) | J19: =I19*(1+'P&L'!$B$4) | K19: =J19*(1+'P&L'!$B$4)
A20: Sunday Program (incl. GRÜEZI coffee costs) | B20: 1000 | C20: =B20*(1+'P&L'!$B$4) | D20: =C20*(1+'P&L'!$B$4) | E20: =D20*(1+'P&L'!$B$4) | F20: =E20*(1+'P&L'!$B$4) | G20: =F20*(1+'P&L'!$B$4) | H20: =G20*(1+'P&L'!$B$4) | I20: =H20*(1+'P&L'!$B$4) | J20: =I20*(1+'P&L'!$B$4) | K20: =J20*(1+'P&L'!$B$4)
A22: Category A Subtotal | B22: =B16+B17+B18+B19+B20 | C22: =C16+C17+C18+C19+C20 | D22: =D16+D17+D18+D19+D20 | E22: =E16+E17+E18+E19+E20 | F22: =F16+F17+F18+F19+F20 | G22: =G16+G17+G18+G19+G20 | H22: =H16+H17+H18+H19+H20 | I22: =I16+I17+I18+I19+I20 | ... K22: =K16+K17+K18+K19+K20
A24: CATEGORY B: GUEST-LINKED
B25: 2027 | C25: 2028 | D25: 2029 | E25: 2030 | F25: 2031 | G25: 2032 | H25: 2033 | I25: 2034 | J25: 2035 | K25: 2036
A26: Welcome Drinks (Ticket Count × 2 × CHF 9) | B26: 4500 | C26: =Revenue!$B$5*2*9 | D26: =Revenue!$B$5*2*9 | E26: =Revenue!$B$5*2*9 | F26: =Revenue!$B$5*2*9 | G26: =Revenue!$B$5*2*9 | H26: =Revenue!$B$5*2*9 | I26: =Revenue!$B$5*2*9 | J26: =Revenue!$B$5*2*9 | K26: =Revenue!$B$5*2*9
A27: Security | B27: 4500 | C27: =$B$27 | D27: =$B$27 | E27: =$B$27 | F27: =$B$27 | G27: =$B$27 | H27: =$B$27 | I27: =$B$27 | J27: =$B$27 | K27: =$B$27
A29: Category B Subtotal | B29: =B26+B27 | C29: =C26+C27 | D29: =D26+D27 | E29: =E26+E27 | F29: =F26+F27 | G29: =G26+G27 | H29: =H26+H27 | I29: =I26+I27 | ... K29: =K26+K27
A31: CATEGORY C: AMBITION-LINKED
B32: 2027 | C32: 2028 | D32: 2029 | E32: 2030 | F32: 2031 | G32: 2032 | H32: 2033 | I32: 2034 | J32: 2035 | K32: 2036
A33: Talent (DJs / Artists) | B33: 18000 | C33: =B33*(1+$B$5) | D33: =C33*(1+$B$5) | E33: =D33*(1+$B$5) | F33: =E33*(1+$B$5) | G33: =F33*(1+$B$5) | H33: =G33*(1+$B$5) | I33: =H33*(1+$B$5) | J33: =I33*(1+$B$5) | K33: =J33*(1+$B$5)
A34: Production (Sound / Lighting) | B34: 12000 | C34: =B34*(1+$B$5) | D34: =C34*(1+$B$5) | E34: =D34*(1+$B$5) | F34: =E34*(1+$B$5) | G34: =F34*(1+$B$5) | H34: =G34*(1+$B$5) | I34: =H34*(1+$B$5) | J34: =I34*(1+$B$5) | K34: =J34*(1+$B$5)
A35: Decor / Branding | B35: 3500 | C35: =B35*(1+$B$5) | D35: =C35*(1+$B$5) | E35: =D35*(1+$B$5) | F35: =E35*(1+$B$5) | G35: =F35*(1+$B$5) | H35: =G35*(1+$B$5) | I35: =H35*(1+$B$5) | J35: =I35*(1+$B$5) | K35: =J35*(1+$B$5)
A36: Photo / Video | B36: 5000 | C36: =B36*(1+$B$5) | D36: =C36*(1+$B$5) | E36: =D36*(1+$B$5) | F36: =E36*(1+$B$5) | G36: =F36*(1+$B$5) | H36: =G36*(1+$B$5) | I36: =H36*(1+$B$5) | J36: =I36*(1+$B$5) | K36: =J36*(1+$B$5)
A37: Marketing / Print | B37: 2000 | C37: =B37*(1+$B$5) | D37: =C37*(1+$B$5) | E37: =D37*(1+$B$5) | F37: =E37*(1+$B$5) | G37: =F37*(1+$B$5) | H37: =G37*(1+$B$5) | I37: =H37*(1+$B$5) | J37: =I37*(1+$B$5) | K37: =J37*(1+$B$5)
A38: Operating Partner | B38: 6000 | C38: =B38*(1+$B$5) | D38: =C38*(1+$B$5) | E38: =D38*(1+$B$5) | F38: =E38*(1+$B$5) | G38: =F38*(1+$B$5) | H38: =G38*(1+$B$5) | I38: =H38*(1+$B$5) | J38: =I38*(1+$B$5) | K38: =J38*(1+$B$5)
A39: Chedi Winter Garden (Friday) | B39: 2500 | C39: =B39*(1+$B$5) | D39: =C39*(1+$B$5) | E39: =D39*(1+$B$5) | F39: =E39*(1+$B$5) | G39: =F39*(1+$B$5) | H39: =G39*(1+$B$5) | I39: =H39*(1+$B$5) | J39: =I39*(1+$B$5) | K39: =J39*(1+$B$5)
A41: Category C Subtotal | B41: =B33+B34+B35+B36+B37+B38+B39 | C41: =C33+C34+C35+C36+C37+C38+C39 | D41: =D33+D34+D35+D36+D37+D38+D39 | E41: =E33+E34+E35+E36+E37+E38+E39 | F41: =F33+F34+F35+F36+F37+F38+F39 | G41: =G33+G34+G35+G36+G37+G38+G39 | H41: =H33+H34+H35+H36+H37+H38+H39 | I41: =I33+I34+I35+I36+I37+I38+I39 | ... K41: =K33+K34+K35+K36+K37+K38+K39
A43: DIRECT COST TOTALS
B44: 2027 | C44: 2028 | D44: 2029 | E44: 2030 | F44: 2031 | G44: 2032 | H44: 2033 | I44: 2034 | J44: 2035 | K44: 2036
A45: Direct Cost Subtotal (A+B+C) | B45: =B22+B29+B41 | C45: =C22+C29+C41 | D45: =D22+D29+D41 | E45: =E22+E29+E41 | F45: =F22+F29+F41 | G45: =G22+G29+G41 | H45: =H22+H29+H41 | I45: =I22+I29+I41 | ... K45: =K22+K29+K41
A46: Contingency | B46: =B45*$B$6 | C46: =C45*$B$6 | D46: =D45*$B$6 | E46: =E45*$B$6 | F46: =F45*$B$6 | G46: =G45*$B$6 | H46: =H45*$B$6 | I46: =I45*$B$6 | ... K46: =K45*$B$6
A47: TOTAL WINTER DIRECT COST | B47: =B45+B46 | C47: =C45+C46 | D47: =D45+D46 | E47: =E45+E46 | F47: =F45+F46 | G47: =G45+G46 | H47: =H45+H46 | I47: =I45+I46 | ... K47: =K45+K46
A48: Summer Cost | B48: =IF(2027>=Revenue!$B$13,B47*Revenue!$B$12,0) | C48: =IF(2028>=Revenue!$B$13,C47*Revenue!$B$12,0) | D48: =IF(2029>=Revenue!$B$13,D47*Revenue!$B$12,0) | E48: =IF(2030>=Revenue!$B$13,E47*Revenue!$B$12,0) | F48: =IF(2031>=Revenue!$B$13,F47*Revenue!$B$12,0) | G48: =IF(2032>=Revenue!$B$13,G47*Revenue!$B$12,0) | H48: =IF(2033>=Revenue!$B$13,H47*Revenue!$B$12,0) | I48: =IF(2034>=Revenue!$B$13,I47*Revenue!$B$12,0) | J48: =IF(2035>=Revenue!$B$13,J47*Revenue!$B$12,0) | K48: =IF(2036>=Revenue!$B$13,K47*Revenue!$B$12,0)
A49: TOTAL ANNUAL DIRECT COST | B49: =B47+B48 | C49: =C47+C48 | D49: =D47+D48 | E49: =E47+E48 | F49: =F47+F48 | G49: =G47+G48 | H49: =H47+H48 | I49: =I47+I48 | ... K49: =K47+K48
A51: OVERHEAD & FOUNDER PAY
B52: 2027 | C52: 2028 | D52: 2029 | E52: 2030 | F52: 2031 | G52: 2032 | H52: 2033 | I52: 2034 | J52: 2035 | K52: 2036
A53: Overhead (manual input) | B53: 8000 | C53: 8000 | D53: 8000 | E53: 39000 | F53: 39000 | G53: 39000 | H53: 55000 | I53: 56000 | J53: 58000 | K53: 60000
A54: Overhead jumps when new hires are added (part-time producer in 2030, additional staff in 2033). Cannot be modeled with a growth rate.
A55: Founder Pay (2027-2031: manual / 2032+: auto +4%/yr) | B55: 10000 | C55: 20000 | D55: 30000 | E55: 50000 | F55: 70000 | G55: =F55*1.04 | H55: =G55*1.04 | I55: =H55*1.04 | J55: =I55*1.04 | K55: =J55*1.04
A57: TOTAL COST | B57: =B49+B53+B55 | C57: =C49+C53+C55 | D57: =D49+D53+D55 | E57: =E49+E53+E55 | F57: =F49+F53+F55 | G57: =G49+G53+G55 | H57: =H49+H53+H55 | I57: =I49+I53+I55 | ... K57: =K49+K53+K55
